hoomd_flowws/DEMInteraction.py
hoomd_flowws/Damasceno2017Interaction.py
hoomd_flowws/Init.py
hoomd_flowws/Interaction.py
hoomd_flowws/Run.py
hoomd_flowws/RunHPMC.py
hoomd_flowws/ShapeDefinition.py
hoomd_flowws/__init__.py
hoomd_flowws/internal.py
hoomd_flowws/version.py
hoomd_flowws-0.1.dist-info/LICENSE
hoomd_flowws-0.1.dist-info/METADATA
hoomd_flowws-0.1.dist-info/WHEEL
hoomd_flowws-0.1.dist-info/entry_points.txt
hoomd_flowws-0.1.dist-info/top_level.txt
hoomd_flowws-0.1.dist-info/RECORD
