Metadata-Version: 2.1
Name: hoomd-flowws
Version: 0.1
Summary: Stage-based scientific workflows using HOOMD-Blue
Home-page: UNKNOWN
Author: Matthew Spellings
Author-email: matthew.p.spellings@gmail.com
License: MIT
Platform: UNKNOWN
Classifier: Development Status :: 3 - Alpha
Classifier: License :: OSI Approved :: MIT License
Classifier: Programming Language :: Python :: 3
Requires-Python: >=3
Requires-Dist: flowws
